eznorm/__init__.py
eznorm/test.py
eznorm-0.0.0.dist-info/METADATA
eznorm-0.0.0.dist-info/WHEEL
eznorm-0.0.0.dist-info/top_level.txt
eznorm-0.0.0.dist-info/RECORD
